{
	"name": "first_Bulk_insert_copy1",
	"properties": {
		"activities": [
			{
				"name": "ForEach1",
				"type": "ForEach",
				"dependsOn": [
					{
						"activity": "Lookup1",
						"dependencyConditions": [
							"Succeeded"
						]
					}
				],
				"userProperties": [],
				"typeProperties": {
					"items": {
						"value": "@activity('Lookup1').output.value",
						"type": "Expression"
					},
					"isSequential": true,
					"activities": [
						{
							"name": "Bulk insert for",
							"type": "SqlServerStoredProcedure",
							"dependsOn": [],
							"policy": {
								"timeout": "7.00:00:00",
								"retry": 0,
								"retryIntervalInSeconds": 30,
								"secureOutput": false,
								"secureInput": false
							},
							"userProperties": [],
							"typeProperties": {
								"storedProcedureName": "[dbo].[usp_BULK]",
								"storedProcedureParameters": {
									"AmountColumn": {
										"value": {
											"value": "@item().AmountColumn",
											"type": "Expression"
										},
										"type": "String"
									},
									"Check_Existence": {
										"value": {
											"value": "@item().Check_Existence",
											"type": "Expression"
										},
										"type": "Byte[]"
									},
									"ClearTable": {
										"value": {
											"value": "@item().ClearTable",
											"type": "Expression"
										},
										"type": "Byte[]"
									},
									"FileHandle": {
										"value": {
											"value": "@item().FileHandle",
											"type": "Expression"
										},
										"type": "Int32"
									},
									"FirstRow": {
										"value": {
											"value": "@item().FirstRows",
											"type": "Expression"
										},
										"type": "Int32"
									},
									"FormatFileName": {
										"value": {
											"value": "@item().FormatFileName",
											"type": "Expression"
										},
										"type": "String"
									},
									"FormatFilePath": {
										"value": {
											"value": "@item().FormatFilePath",
											"type": "Expression"
										},
										"type": "String"
									},
									"PostDate": {
										"value": {
											"value": "@item().PostDate",
											"type": "Expression"
										},
										"type": "String"
									},
									"RawFileName": {
										"value": {
											"value": "@item().RawFileName",
											"type": "Expression"
										},
										"type": "String"
									},
									"RawFilePath": {
										"value": {
											"value": "@item().FilePath",
											"type": "Expression"
										},
										"type": "String"
									},
									"RawTableName": {
										"value": {
											"value": "@item().TableName",
											"type": "Expression"
										},
										"type": "String"
									}
								}
							},
							"linkedServiceName": {
								"referenceName": "localsqldb",
								"type": "LinkedServiceReference"
							}
						}
					]
				}
			},
			{
				"name": "Lookup1",
				"type": "Lookup",
				"dependsOn": [],
				"policy": {
					"timeout": "7.00:00:00",
					"retry": 0,
					"retryIntervalInSeconds": 30,
					"secureOutput": false,
					"secureInput": false
				},
				"userProperties": [],
				"typeProperties": {
					"source": {
						"type": "SqlServerSource",
						"sqlReaderQuery": "SELECT * from [dbo].[cfgSubmissionInfo]\n",
						"queryTimeout": "02:00:00",
						"partitionOption": "None"
					},
					"dataset": {
						"referenceName": "SqlServerTable1",
						"type": "DatasetReference"
					},
					"firstRowOnly": false
				}
			}
		],
		"folder": {
			"name": "ETL"
		},
		"annotations": []
	}
}